xwtools/ReParse.py
xwtools/SM2.py
xwtools/SM4.py
xwtools/TextSimilarity.py
xwtools/__init__.py
xwtools/cache_func.py
xwtools/chinese2digits.py
xwtools/config_log.py
xwtools/cut_word.py
xwtools/data_to_str.py
xwtools/db_op.py
xwtools/django.py
xwtools/elasticsearch_op.py
xwtools/email.py
xwtools/encrypt.py
xwtools/es.py
xwtools/etl_time.py
xwtools/get-pip.py
xwtools/hive_op.py
xwtools/jwt_token.py
xwtools/mongo_op.py
xwtools/mq_api.py
xwtools/mq_decode.py
xwtools/multi_process.py
xwtools/multi_process_thread.py
xwtools/multi_thread_auto.py
xwtools/mysql.py
xwtools/mysql_op.py
xwtools/neo4j_op.py
xwtools/object_id.py
xwtools/plt_graph.py
xwtools/queue0.py
xwtools/queue2.py
xwtools/queue_main.py
xwtools/redis_operate.py
xwtools/run_on_time.py
xwtools/spider_op.py
xwtools/sqlalchemy.py
xwtools/sqlite_op.py
xwtools/sqlserver_op.py
xwtools/strQB.py
xwtools/text_process.py
xwtools/url_uuid.py
xwtools/utils.py
xwtools/wechat.py
xwtools-2.1.3.dist-info/METADATA
xwtools-2.1.3.dist-info/WHEEL
xwtools-2.1.3.dist-info/top_level.txt
xwtools-2.1.3.dist-info/RECORD
