Metadata-Version: 2.1
Name: xwtools
Version: 2.1.3
Summary: xwtools
Home-page: https://github.com/xulehexuwei
Author: xuwei
Author-email: 15200813194@163.com
License: BSD License
Classifier: Environment :: Web Environment
Classifier: Intended Audience :: Developers
Classifier: License :: OSI Approved :: BSD License
Classifier: Operating System :: OS Independent
Classifier: Programming Language :: Python :: 3.6
Classifier: Topic :: Internet :: WWW/HTTP
Classifier: Topic :: Internet :: WWW/HTTP :: Dynamic Content
Requires-Dist: pika>=1.3.1
Requires-Dist: numpy>=1.21.5
Requires-Dist: shortuuid>=1.0.11
Requires-Dist: threadpool>=1.3.2
Requires-Dist: redis>=4.4.0
Requires-Dist: elasticsearch>=7.9.1
Requires-Dist: elasticsearch_dsl>=7.4.0
Requires-Dist: matplotlib>=3.5.1
Requires-Dist: jieba>=0.42.1
Requires-Dist: wheel>=0.37.1
Requires-Dist: PyMySQL>=1.0.2
Requires-Dist: pypinyin>=0.47.1
Requires-Dist: selenium==4.7.2
Requires-Dist: pymongo>=3.11.0
Requires-Dist: openpyxl>=3.0.9
Requires-Dist: pandas>=1.4.2
Requires-Dist: requests>=2.27.1
Requires-Dist: beautifulsoup4>=4.10.0
Requires-Dist: sqlalchemy>=1.4.32
Requires-Dist: graypy>=2.1.0
